pulumi-maas/__init__.py
pulumi-maas/_inputs.py
pulumi-maas/_utilities.py
pulumi-maas/block_device.py
pulumi-maas/dns_domain.py
pulumi-maas/dns_record.py
pulumi-maas/fabric.py
pulumi-maas/get_fabric.py
pulumi-maas/get_subnet.py
pulumi-maas/get_vlan.py
pulumi-maas/instance.py
pulumi-maas/machine.py
pulumi-maas/network_interface_link.py
pulumi-maas/network_interface_physical.py
pulumi-maas/outputs.py
pulumi-maas/provider.py
pulumi-maas/pulumi-plugin.json
pulumi-maas/py.typed
pulumi-maas/space.py
pulumi-maas/subnet.py
pulumi-maas/subnet_ip_range.py
pulumi-maas/tag.py
pulumi-maas/user.py
pulumi-maas/vlan.py
pulumi-maas/vm_host.py
pulumi-maas/vm_host_machine.py
pulumi-maas/config/__init__.py
pulumi-maas/config/vars.py
pulumi_maas/__init__.py
pulumi_maas/_inputs.py
pulumi_maas/_utilities.py
pulumi_maas/block_device.py
pulumi_maas/dns_domain.py
pulumi_maas/dns_record.py
pulumi_maas/fabric.py
pulumi_maas/get_fabric.py
pulumi_maas/get_subnet.py
pulumi_maas/get_vlan.py
pulumi_maas/instance.py
pulumi_maas/machine.py
pulumi_maas/network_interface_link.py
pulumi_maas/network_interface_physical.py
pulumi_maas/outputs.py
pulumi_maas/provider.py
pulumi_maas/space.py
pulumi_maas/subnet.py
pulumi_maas/subnet_ip_range.py
pulumi_maas/tag.py
pulumi_maas/user.py
pulumi_maas/vlan.py
pulumi_maas/vm_host.py
pulumi_maas/vm_host_machine.py
pulumi_maas/config/__init__.py
pulumi_maas/config/vars.py
pulumi_maas-1.0.3.dist-info/METADATA
pulumi_maas-1.0.3.dist-info/WHEEL
pulumi_maas-1.0.3.dist-info/top_level.txt
pulumi_maas-1.0.3.dist-info/RECORD
