Metadata-Version: 2.1
Name: pulumi-maas
Version: 1.0.3
Summary: A Pulumi package for creating and managing Canonical Metal-As-A-Service (MAAS) resources.
Home-page: https://www.pulumi.com
License: Apache-2.0
Project-URL: Repository, https://github.com/juhnny5/pulumi-maas-python
Keywords: pulumi maas category/cloud
Requires-Python: >=3.7
Requires-Dist: parver (>=0.2.1)
Requires-Dist: pulumi (<4.0.0,>=3.0.0)
Requires-Dist: semver (>=2.8.1)
